type_cellar/__init__.py
type_cellar/_types.py
type_cellar/enums.py
type_cellar/py.typed
type_cellar/wrappers.py
type_cellar-0.1.0.dist-info/METADATA
type_cellar-0.1.0.dist-info/WHEEL
type_cellar-0.1.0.dist-info/RECORD
