Metadata-Version: 2.4
Name: type-cellar
Version: 0.1.0
Summary: Common types I use across projects.
Author-email: Alexander Socarras <apsocarras@gmail.com>
Requires-Python: >=3.10
Requires-Dist: typing-extensions>=4.15.0
Requires-Dist: useful-types>=0.2.1
